[
 {"country" : "Aruba", "val": "Dutch"},
 {"country" : "Aruba", "val": "English"},
 {"country" : "Aruba", "val": "Papiamento"},
 {"country" : "Aruba", "val": "Spanish"},
 {"country" : "Afghanistan", "val": "Balochi"},
 {"country" : "Afghanistan", "val": "Dari"},
 {"country" : "Afghanistan", "val": "Pashto"},
 {"country" : "Afghanistan", "val": "Turkmenian"},
 {"country" : "Afghanistan", "val": "Uzbek"},
 {"country" : "Angola", "val": "Ambo"},
 {"country" : "Angola", "val": "Chokwe"},
 {"country" : "Angola", "val": "Kongo"},
 {"country" : "Angola", "val": "Luchazi"},
 {"country" : "Angola", "val": "Luimbe-nganguela"},
 {"country" : "Angola", "val": "Luvale"},
 {"country" : "Angola", "val": "Mbundu"},
 {"country" : "Angola", "val": "Nyaneka-nkhumbi"},
 {"country" : "Angola", "val": "Ovimbundu"},
 {"country" : "Anguilla", "val": "English"},
 {"country" : "Albania", "val": "Albaniana"},
 {"country" : "Albania", "val": "Greek"},
 {"country" : "Albania", "val": "Macedonian"},
 {"country" : "Andorra", "val": "Catalan"},
 {"country" : "Andorra", "val": "French"},
 {"country" : "Andorra", "val": "Portuguese"},
 {"country" : "Andorra", "val": "Spanish"},
 {"country" : "Netherlands Antilles", "val": "Dutch"},
 {"country" : "Netherlands Antilles", "val": "English"},
 {"country" : "Netherlands Antilles", "val": "Papiamento"},
 {"country" : "United Arab Emirates", "val": "Arabic"},
 {"country" : "United Arab Emirates", "val": "Hindi"},
 {"country" : "Argentina", "val": "Indian Languages"},
 {"country" : "Argentina", "val": "Italian"},
 {"country" : "Argentina", "val": "Spanish"},
 {"country" : "Armenia", "val": "Armenian"},
 {"country" : "Armenia", "val": "Azerbaijani"},
 {"country" : "American Samoa", "val": "English"},
 {"country" : "American Samoa", "val": "Samoan"},
 {"country" : "American Samoa", "val": "Tongan"},
 {"country" : "Antigua and Barbuda", "val": "Creole English"},
 {"country" : "Antigua and Barbuda", "val": "English"},
 {"country" : "Australia", "val": "Arabic"},
 {"country" : "Australia", "val": "Canton Chinese"},
 {"country" : "Australia", "val": "English"},
 {"country" : "Australia", "val": "German"},
 {"country" : "Australia", "val": "Greek"},
 {"country" : "Australia", "val": "Italian"},
 {"country" : "Australia", "val": "Serbo-Croatian"},
 {"country" : "Australia", "val": "Vietnamese"},
 {"country" : "Austria", "val": "Czech"},
 {"country" : "Austria", "val": "German"},
 {"country" : "Austria", "val": "Hungarian"},
 {"country" : "Austria", "val": "Polish"},
 {"country" : "Austria", "val": "Romanian"},
 {"country" : "Austria", "val": "Serbo-Croatian"},
 {"country" : "Austria", "val": "Slovene"},
 {"country" : "Austria", "val": "Turkish"},
 {"country" : "Azerbaijan", "val": "Armenian"},
 {"country" : "Azerbaijan", "val": "Azerbaijani"},
 {"country" : "Azerbaijan", "val": "Lezgian"},
 {"country" : "Azerbaijan", "val": "Russian"},
 {"country" : "Burundi", "val": "French"},
 {"country" : "Burundi", "val": "Kirundi"},
 {"country" : "Burundi", "val": "Swahili"},
 {"country" : "Belgium", "val": "Arabic"},
 {"country" : "Belgium", "val": "Dutch"},
 {"country" : "Belgium", "val": "French"},
 {"country" : "Belgium", "val": "German"},
 {"country" : "Belgium", "val": "Italian"},
 {"country" : "Belgium", "val": "Turkish"},
 {"country" : "Benin", "val": "Adja"},
 {"country" : "Benin", "val": "Aizo"},
 {"country" : "Benin", "val": "Bariba"},
 {"country" : "Benin", "val": "Fon"},
 {"country" : "Benin", "val": "Ful"},
 {"country" : "Benin", "val": "Joruba"},
 {"country" : "Benin", "val": "Somba"},
 {"country" : "Burkina Faso", "val": "Busansi"},
 {"country" : "Burkina Faso", "val": "Dagara"},
 {"country" : "Burkina Faso", "val": "Dyula"},
 {"country" : "Burkina Faso", "val": "Ful"},
 {"country" : "Burkina Faso", "val": "Gurma"},
 {"country" : "Burkina Faso", "val": "Mossi"},
 {"country" : "Bangladesh", "val": "Bengali"},
 {"country" : "Bangladesh", "val": "Chakma"},
 {"country" : "Bangladesh", "val": "Garo"},
 {"country" : "Bangladesh", "val": "Khasi"},
 {"country" : "Bangladesh", "val": "Marma"},
 {"country" : "Bangladesh", "val": "Santhali"},
 {"country" : "Bangladesh", "val": "Tripuri"},
 {"country" : "Bulgaria", "val": "Bulgariana"},
 {"country" : "Bulgaria", "val": "Macedonian"},
 {"country" : "Bulgaria", "val": "Romani"},
 {"country" : "Bulgaria", "val": "Turkish"},
 {"country" : "Bahrain", "val": "Arabic"},
 {"country" : "Bahrain", "val": "English"},
 {"country" : "Bahamas", "val": "Creole English"},
 {"country" : "Bahamas", "val": "Creole French"},
 {"country" : "Bosnia and Herzegovina", "val": "Serbo-Croatian"},
 {"country" : "Belarus", "val": "Belorussian"},
 {"country" : "Belarus", "val": "Polish"},
 {"country" : "Belarus", "val": "Russian"},
 {"country" : "Belarus", "val": "Ukrainian"},
 {"country" : "Belize", "val": "English"},
 {"country" : "Belize", "val": "Garifuna"},
 {"country" : "Belize", "val": "Maya Languages"},
 {"country" : "Belize", "val": "Spanish"},
 {"country" : "Bermuda", "val": "English"},
 {"country" : "Bolivia", "val": "Aimará"},
 {"country" : "Bolivia", "val": "Guaraní"},
 {"country" : "Bolivia", "val": "Ketua"},
 {"country" : "Bolivia", "val": "Spanish"},
 {"country" : "Brazil", "val": "German"},
 {"country" : "Brazil", "val": "Indian Languages"},
 {"country" : "Brazil", "val": "Italian"},
 {"country" : "Brazil", "val": "Japanese"},
 {"country" : "Brazil", "val": "Portuguese"},
 {"country" : "Barbados", "val": "Bajan"},
 {"country" : "Barbados", "val": "English"},
 {"country" : "Brunei", "val": "Chinese"},
 {"country" : "Brunei", "val": "English"},
 {"country" : "Brunei", "val": "Malay"},
 {"country" : "Brunei", "val": "Malay-English"},
 {"country" : "Bhutan", "val": "Asami"},
 {"country" : "Bhutan", "val": "Dzongkha"},
 {"country" : "Bhutan", "val": "Nepali"},
 {"country" : "Botswana", "val": "Khoekhoe"},
 {"country" : "Botswana", "val": "Ndebele"},
 {"country" : "Botswana", "val": "San"},
 {"country" : "Botswana", "val": "Shona"},
 {"country" : "Botswana", "val": "Tswana"},
 {"country" : "Central African Republic", "val": "Banda"},
 {"country" : "Central African Republic", "val": "Gbaya"},
 {"country" : "Central African Republic", "val": "Mandjia"},
 {"country" : "Central African Republic", "val": "Mbum"},
 {"country" : "Central African Republic", "val": "Ngbaka"},
 {"country" : "Central African Republic", "val": "Sara"},
 {"country" : "Canada", "val": "Chinese"},
 {"country" : "Canada", "val": "Dutch"},
 {"country" : "Canada", "val": "English"},
 {"country" : "Canada", "val": "Eskimo Languages"},
 {"country" : "Canada", "val": "French"},
 {"country" : "Canada", "val": "German"},
 {"country" : "Canada", "val": "Italian"},
 {"country" : "Canada", "val": "Polish"},
 {"country" : "Canada", "val": "Portuguese"},
 {"country" : "Canada", "val": "Punjabi"},
 {"country" : "Canada", "val": "Spanish"},
 {"country" : "Canada", "val": "Ukrainian"},
 {"country" : "Cocos (Keeling) Islands", "val": "English"},
 {"country" : "Cocos (Keeling) Islands", "val": "Malay"},
 {"country" : "Switzerland", "val": "French"},
 {"country" : "Switzerland", "val": "German"},
 {"country" : "Switzerland", "val": "Italian"},
 {"country" : "Switzerland", "val": "Romansh"},
 {"country" : "Chile", "val": "Aimará"},
 {"country" : "Chile", "val": "Araucan"},
 {"country" : "Chile", "val": "Rapa nui"},
 {"country" : "Chile", "val": "Spanish"},
 {"country" : "China", "val": "Chinese"},
 {"country" : "China", "val": "Dong"},
 {"country" : "China", "val": "Hui"},
 {"country" : "China", "val": "Mantu"},
 {"country" : "China", "val": "Miao"},
 {"country" : "China", "val": "Mongolian"},
 {"country" : "China", "val": "Puyi"},
 {"country" : "China", "val": "Tibetan"},
 {"country" : "China", "val": "Tujia"},
 {"country" : "China", "val": "Uighur"},
 {"country" : "China", "val": "Yi"},
 {"country" : "China", "val": "Zhuang"},
 {"country" : "Ivory Coast", "val": "Akan"},
 {"country" : "Ivory Coast", "val": "Gur"},
 {"country" : "Ivory Coast", "val": "Kru"},
 {"country" : "Ivory Coast", "val": "Malinke"},
 {"country" : "Ivory Coast", "val": "[South]Mande"},
 {"country" : "Cameroon", "val": "Bamileke-bamum"},
 {"country" : "Cameroon", "val": "Duala"},
 {"country" : "Cameroon", "val": "Fang"},
 {"country" : "Cameroon", "val": "Ful"},
 {"country" : "Cameroon", "val": "Maka"},
 {"country" : "Cameroon", "val": "Mandara"},
 {"country" : "Cameroon", "val": "Masana"},
 {"country" : "Cameroon", "val": "Tikar"},
 {"country" : "Congo, The Democratic Republic of the", "val": "Boa"},
 {"country" : "Congo, The Democratic Republic of the", "val": "Chokwe"},
 {"country" : "Congo, The Democratic Republic of the", "val": "Kongo"},
 {"country" : "Congo, The Democratic Republic of the", "val": "Luba"},
 {"country" : "Congo, The Democratic Republic of the", "val": "Mongo"},
 {"country" : "Congo, The Democratic Republic of the", "val": "Ngala and Bangi"},
 {"country" : "Congo, The Democratic Republic of the", "val": "Rundi"},
 {"country" : "Congo, The Democratic Republic of the", "val": "Rwanda"},
 {"country" : "Congo, The Democratic Republic of the", "val": "Teke"},
 {"country" : "Congo, The Democratic Republic of the", "val": "Zande"},
 {"country" : "Congo", "val": "Kongo"},
 {"country" : "Congo", "val": "Mbete"},
 {"country" : "Congo", "val": "Mboshi"},
 {"country" : "Congo", "val": "Punu"},
 {"country" : "Congo", "val": "Sango"},
 {"country" : "Congo", "val": "Teke"},
 {"country" : "Cook Islands", "val": "English"},
 {"country" : "Cook Islands", "val": "Maori"},
 {"country" : "Colombia", "val": "Arawakan"},
 {"country" : "Colombia", "val": "Caribbean"},
 {"country" : "Colombia", "val": "Chibcha"},
 {"country" : "Colombia", "val": "Creole English"},
 {"country" : "Colombia", "val": "Spanish"},
 {"country" : "Comoros", "val": "Comorian"},
 {"country" : "Comoros", "val": "Comorian-Arabic"},
 {"country" : "Comoros", "val": "Comorian-French"},
 {"country" : "Comoros", "val": "Comorian-madagassi"},
 {"country" : "Comoros", "val": "Comorian-Swahili"},
 {"country" : "Cape Verde", "val": "Crioulo"},
 {"country" : "Cape Verde", "val": "Portuguese"},
 {"country" : "Costa Rica", "val": "Chibcha"},
 {"country" : "Costa Rica", "val": "Chinese"},
 {"country" : "Costa Rica", "val": "Creole English"},
 {"country" : "Costa Rica", "val": "Spanish"},
 {"country" : "Cuba", "val": "Spanish"},
 {"country" : "Christmas Island", "val": "Chinese"},
 {"country" : "Christmas Island", "val": "English"},
 {"country" : "Cayman Islands", "val": "English"},
 {"country" : "Cyprus", "val": "Greek"},
 {"country" : "Cyprus", "val": "Turkish"},
 {"country" : "Czech Republic", "val": "Czech"},
 {"country" : "Czech Republic", "val": "German"},
 {"country" : "Czech Republic", "val": "Hungarian"},
 {"country" : "Czech Republic", "val": "Moravian"},
 {"country" : "Czech Republic", "val": "Polish"},
 {"country" : "Czech Republic", "val": "Romani"},
 {"country" : "Czech Republic", "val": "Silesiana"},
 {"country" : "Czech Republic", "val": "Slovak"},
 {"country" : "Germany", "val": "German"},
 {"country" : "Germany", "val": "Greek"},
 {"country" : "Germany", "val": "Italian"},
 {"country" : "Germany", "val": "Polish"},
 {"country" : "Germany", "val": "Southern Slavic Languages"},
 {"country" : "Germany", "val": "Turkish"},
 {"country" : "Djibouti", "val": "Afar"},
 {"country" : "Djibouti", "val": "Arabic"},
 {"country" : "Djibouti", "val": "Somali"},
 {"country" : "Dominica", "val": "Creole English"},
 {"country" : "Dominica", "val": "Creole French"},
 {"country" : "Denmark", "val": "Arabic"},
 {"country" : "Denmark", "val": "Danish"},
 {"country" : "Denmark", "val": "English"},
 {"country" : "Denmark", "val": "German"},
 {"country" : "Denmark", "val": "Norwegian"},
 {"country" : "Denmark", "val": "Swedish"},
 {"country" : "Denmark", "val": "Turkish"},
 {"country" : "Dominican Republic", "val": "Creole French"},
 {"country" : "Dominican Republic", "val": "Spanish"},
 {"country" : "Algeria", "val": "Arabic"},
 {"country" : "Algeria", "val": "Berberi"},
 {"country" : "Ecuador", "val": "Ketua"},
 {"country" : "Ecuador", "val": "Spanish"},
 {"country" : "Egypt", "val": "Arabic"},
 {"country" : "Egypt", "val": "Sinaberberi"},
 {"country" : "Eritrea", "val": "Afar"},
 {"country" : "Eritrea", "val": "Bilin"},
 {"country" : "Eritrea", "val": "Hadareb"},
 {"country" : "Eritrea", "val": "Saho"},
 {"country" : "Eritrea", "val": "Tigre"},
 {"country" : "Eritrea", "val": "Tigrigna"},
 {"country" : "Western Sahara", "val": "Arabic"},
 {"country" : "Spain", "val": "Basque"},
 {"country" : "Spain", "val": "Catalan"},
 {"country" : "Spain", "val": "Galecian"},
 {"country" : "Spain", "val": "Spanish"},
 {"country" : "Estonia", "val": "Belorussian"},
 {"country" : "Estonia", "val": "Estonian"},
 {"country" : "Estonia", "val": "Finnish"},
 {"country" : "Estonia", "val": "Russian"},
 {"country" : "Estonia", "val": "Ukrainian"},
 {"country" : "Ethiopia", "val": "Amharic"},
 {"country" : "Ethiopia", "val": "Gurage"},
 {"country" : "Ethiopia", "val": "Oromo"},
 {"country" : "Ethiopia", "val": "Sidamo"},
 {"country" : "Ethiopia", "val": "Somali"},
 {"country" : "Ethiopia", "val": "Tigrigna"},
 {"country" : "Ethiopia", "val": "Walaita"},
 {"country" : "Finland", "val": "Estonian"},
 {"country" : "Finland", "val": "Finnish"},
 {"country" : "Finland", "val": "Russian"},
 {"country" : "Finland", "val": "Saame"},
 {"country" : "Finland", "val": "Swedish"},
 {"country" : "Fiji Islands", "val": "Fijian"},
 {"country" : "Fiji Islands", "val": "Hindi"},
 {"country" : "Falkland Islands", "val": "English"},
 {"country" : "France", "val": "Arabic"},
 {"country" : "France", "val": "French"},
 {"country" : "France", "val": "Italian"},
 {"country" : "France", "val": "Portuguese"},
 {"country" : "France", "val": "Spanish"},
 {"country" : "France", "val": "Turkish"},
 {"country" : "Faroe Islands", "val": "Danish"},
 {"country" : "Faroe Islands", "val": "Faroese"},
 {"country" : "Micronesia, Federated States of", "val": "Kosrean"},
 {"country" : "Micronesia, Federated States of", "val": "Mortlock"},
 {"country" : "Micronesia, Federated States of", "val": "Pohnpei"},
 {"country" : "Micronesia, Federated States of", "val": "Trukese"},
 {"country" : "Micronesia, Federated States of", "val": "Wolea"},
 {"country" : "Micronesia, Federated States of", "val": "Yap"},
 {"country" : "Gabon", "val": "Fang"},
 {"country" : "Gabon", "val": "Mbete"},
 {"country" : "Gabon", "val": "Mpongwe"},
 {"country" : "Gabon", "val": "Punu-sira-nzebi"},
 {"country" : "United Kingdom", "val": "English"},
 {"country" : "United Kingdom", "val": "Gaeli"},
 {"country" : "United Kingdom", "val": "Kymri"},
 {"country" : "Georgia", "val": "Abhyasi"},
 {"country" : "Georgia", "val": "Armenian"},
 {"country" : "Georgia", "val": "Azerbaijani"},
 {"country" : "Georgia", "val": "Georgiana"},
 {"country" : "Georgia", "val": "Osseetti"},
 {"country" : "Georgia", "val": "Russian"},
 {"country" : "Ghana", "val": "Akan"},
 {"country" : "Ghana", "val": "Ewe"},
 {"country" : "Ghana", "val": "Ga-adangme"},
 {"country" : "Ghana", "val": "Gurma"},
 {"country" : "Ghana", "val": "Joruba"},
 {"country" : "Ghana", "val": "Mossi"},
 {"country" : "Gibraltar", "val": "Arabic"},
 {"country" : "Gibraltar", "val": "English"},
 {"country" : "Guinea", "val": "Ful"},
 {"country" : "Guinea", "val": "Kissi"},
 {"country" : "Guinea", "val": "Kpelle"},
 {"country" : "Guinea", "val": "Loma"},
 {"country" : "Guinea", "val": "Malinke"},
 {"country" : "Guinea", "val": "Susu"},
 {"country" : "Guinea", "val": "Yalunka"},
 {"country" : "Guadeloupe", "val": "Creole French"},
 {"country" : "Guadeloupe", "val": "French"},
 {"country" : "Gambia", "val": "Diola"},
 {"country" : "Gambia", "val": "Ful"},
 {"country" : "Gambia", "val": "Malinke"},
 {"country" : "Gambia", "val": "Soninke"},
 {"country" : "Gambia", "val": "Wolof"},
 {"country" : "Guinea-Bissau", "val": "Balante"},
 {"country" : "Guinea-Bissau", "val": "Crioulo"},
 {"country" : "Guinea-Bissau", "val": "Ful"},
 {"country" : "Guinea-Bissau", "val": "Malinke"},
 {"country" : "Guinea-Bissau", "val": "Mandyako"},
 {"country" : "Guinea-Bissau", "val": "Portuguese"},
 {"country" : "Equatorial Guinea", "val": "Bubi"},
 {"country" : "Equatorial Guinea", "val": "Fang"},
 {"country" : "Greece", "val": "Greek"},
 {"country" : "Greece", "val": "Turkish"},
 {"country" : "Grenada", "val": "Creole English"},
 {"country" : "Greenland", "val": "Danish"},
 {"country" : "Greenland", "val": "Greenlandic"},
 {"country" : "Guatemala", "val": "Cakchiquel"},
 {"country" : "Guatemala", "val": "Kekchí"},
 {"country" : "Guatemala", "val": "Mam"},
 {"country" : "Guatemala", "val": "Quiché"},
 {"country" : "Guatemala", "val": "Spanish"},
 {"country" : "French Guiana", "val": "Creole French"},
 {"country" : "French Guiana", "val": "Indian Languages"},
 {"country" : "Guam", "val": "Chamorro"},
 {"country" : "Guam", "val": "English"},
 {"country" : "Guam", "val": "Japanese"},
 {"country" : "Guam", "val": "Korean"},
 {"country" : "Guam", "val": "Philippene Languages"},
 {"country" : "Guyana", "val": "Arawakan"},
 {"country" : "Guyana", "val": "Caribbean"},
 {"country" : "Guyana", "val": "Creole English"},
 {"country" : "Hong Kong", "val": "Canton Chinese"},
 {"country" : "Hong Kong", "val": "Chiu chau"},
 {"country" : "Hong Kong", "val": "English"},
 {"country" : "Hong Kong", "val": "Fukien"},
 {"country" : "Hong Kong", "val": "Hakka"},
 {"country" : "Honduras", "val": "Creole English"},
 {"country" : "Honduras", "val": "Garifuna"},
 {"country" : "Honduras", "val": "Miskito"},
 {"country" : "Honduras", "val": "Spanish"},
 {"country" : "Croatia", "val": "Serbo-Croatian"},
 {"country" : "Croatia", "val": "Slovene"},
 {"country" : "Haiti", "val": "French"},
 {"country" : "Haiti", "val": "Haiti Creole"},
 {"country" : "Hungary", "val": "German"},
 {"country" : "Hungary", "val": "Hungarian"},
 {"country" : "Hungary", "val": "Romani"},
 {"country" : "Hungary", "val": "Romanian"},
 {"country" : "Hungary", "val": "Serbo-Croatian"},
 {"country" : "Hungary", "val": "Slovak"},
 {"country" : "Indonesia", "val": "Bahasa"},
 {"country" : "Indonesia", "val": "Bali"},
 {"country" : "Indonesia", "val": "Banja"},
 {"country" : "Indonesia", "val": "Batakki"},
 {"country" : "Indonesia", "val": "Bugi"},
 {"country" : "Indonesia", "val": "Javanese"},
 {"country" : "Indonesia", "val": "Madura"},
 {"country" : "Indonesia", "val": "Malay"},
 {"country" : "Indonesia", "val": "Minangkabau"},
 {"country" : "Indonesia", "val": "Sunda"},
 {"country" : "India", "val": "Asami"},
 {"country" : "India", "val": "Bengali"},
 {"country" : "India", "val": "Gujarati"},
 {"country" : "India", "val": "Hindi"},
 {"country" : "India", "val": "Kannada"},
 {"country" : "India", "val": "Malajalam"},
 {"country" : "India", "val": "Marathi"},
 {"country" : "India", "val": "Orija"},
 {"country" : "India", "val": "Punjabi"},
 {"country" : "India", "val": "Tamil"},
 {"country" : "India", "val": "Telugu"},
 {"country" : "India", "val": "Urdu"},
 {"country" : "Ireland", "val": "English"},
 {"country" : "Ireland", "val": "Irish"},
 {"country" : "Iran", "val": "Arabic"},
 {"country" : "Iran", "val": "Azerbaijani"},
 {"country" : "Iran", "val": "Bakhtyari"},
 {"country" : "Iran", "val": "Balochi"},
 {"country" : "Iran", "val": "Gilaki"},
 {"country" : "Iran", "val": "Kurdish"},
 {"country" : "Iran", "val": "Luri"},
 {"country" : "Iran", "val": "Mazandarani"},
 {"country" : "Iran", "val": "Persian"},
 {"country" : "Iran", "val": "Turkmenian"},
 {"country" : "Iraq", "val": "Arabic"},
 {"country" : "Iraq", "val": "Assyrian"},
 {"country" : "Iraq", "val": "Azerbaijani"},
 {"country" : "Iraq", "val": "Kurdish"},
 {"country" : "Iraq", "val": "Persian"},
 {"country" : "Iceland", "val": "English"},
 {"country" : "Iceland", "val": "Icelandic"},
 {"country" : "Israel", "val": "Arabic"},
 {"country" : "Israel", "val": "Hebrew"},
 {"country" : "Israel", "val": "Russian"},
 {"country" : "Italy", "val": "Albaniana"},
 {"country" : "Italy", "val": "French"},
 {"country" : "Italy", "val": "Friuli"},
 {"country" : "Italy", "val": "German"},
 {"country" : "Italy", "val": "Italian"},
 {"country" : "Italy", "val": "Romani"},
 {"country" : "Italy", "val": "Sardinian"},
 {"country" : "Italy", "val": "Slovene"},
 {"country" : "Jamaica", "val": "Creole English"},
 {"country" : "Jamaica", "val": "Hindi"},
 {"country" : "Jordan", "val": "Arabic"},
 {"country" : "Jordan", "val": "Armenian"},
 {"country" : "Jordan", "val": "Circassian"},
 {"country" : "Japan", "val": "Ainu"},
 {"country" : "Japan", "val": "Chinese"},
 {"country" : "Japan", "val": "English"},
 {"country" : "Japan", "val": "Japanese"},
 {"country" : "Japan", "val": "Korean"},
 {"country" : "Japan", "val": "Philippene Languages"},
 {"country" : "Kazakstan", "val": "German"},
 {"country" : "Kazakstan", "val": "Kazakh"},
 {"country" : "Kazakstan", "val": "Russian"},
 {"country" : "Kazakstan", "val": "Tatar"},
 {"country" : "Kazakstan", "val": "Ukrainian"},
 {"country" : "Kazakstan", "val": "Uzbek"},
 {"country" : "Kenya", "val": "Gusii"},
 {"country" : "Kenya", "val": "Kalenjin"},
 {"country" : "Kenya", "val": "Kamba"},
 {"country" : "Kenya", "val": "Kikuyu"},
 {"country" : "Kenya", "val": "Luhya"},
 {"country" : "Kenya", "val": "Luo"},
 {"country" : "Kenya", "val": "Masai"},
 {"country" : "Kenya", "val": "Meru"},
 {"country" : "Kenya", "val": "Nyika"},
 {"country" : "Kenya", "val": "Turkana"},
 {"country" : "Kyrgyzstan", "val": "Kazakh"},
 {"country" : "Kyrgyzstan", "val": "Kirgiz"},
 {"country" : "Kyrgyzstan", "val": "Russian"},
 {"country" : "Kyrgyzstan", "val": "Tadzhik"},
 {"country" : "Kyrgyzstan", "val": "Tatar"},
 {"country" : "Kyrgyzstan", "val": "Ukrainian"},
 {"country" : "Kyrgyzstan", "val": "Uzbek"},
 {"country" : "Cambodia", "val": "Chinese"},
 {"country" : "Cambodia", "val": "Khmer"},
 {"country" : "Cambodia", "val": "Tam"},
 {"country" : "Cambodia", "val": "Vietnamese"},
 {"country" : "Kiribati", "val": "Kiribati"},
 {"country" : "Kiribati", "val": "Tuvalu"},
 {"country" : "Saint Kitts and Nevis", "val": "Creole English"},
 {"country" : "Saint Kitts and Nevis", "val": "English"},
 {"country" : "South Korea", "val": "Chinese"},
 {"country" : "South Korea", "val": "Korean"},
 {"country" : "Kuwait", "val": "Arabic"},
 {"country" : "Kuwait", "val": "English"},
 {"country" : "Laos", "val": "Lao"},
 {"country" : "Laos", "val": "Lao-Soung"},
 {"country" : "Laos", "val": "Mon-khmer"},
 {"country" : "Laos", "val": "Thai"},
 {"country" : "Lebanon", "val": "Arabic"},
 {"country" : "Lebanon", "val": "Armenian"},
 {"country" : "Lebanon", "val": "French"},
 {"country" : "Liberia", "val": "Bassa"},
 {"country" : "Liberia", "val": "Gio"},
 {"country" : "Liberia", "val": "Grebo"},
 {"country" : "Liberia", "val": "Kpelle"},
 {"country" : "Liberia", "val": "Kru"},
 {"country" : "Liberia", "val": "Loma"},
 {"country" : "Liberia", "val": "Malinke"},
 {"country" : "Liberia", "val": "Mano"},
 {"country" : "Libyan Arab Jamahiriya", "val": "Arabic"},
 {"country" : "Libyan Arab Jamahiriya", "val": "Berberi"},
 {"country" : "Saint Lucia", "val": "Creole French"},
 {"country" : "Saint Lucia", "val": "English"},
 {"country" : "Liechtenstein", "val": "German"},
 {"country" : "Liechtenstein", "val": "Italian"},
 {"country" : "Liechtenstein", "val": "Turkish"},
 {"country" : "Sri Lanka", "val": "Mixed Languages"},
 {"country" : "Sri Lanka", "val": "Singali"},
 {"country" : "Sri Lanka", "val": "Tamil"},
 {"country" : "Lesotho", "val": "English"},
 {"country" : "Lesotho", "val": "Sotho"},
 {"country" : "Lesotho", "val": "Zulu"},
 {"country" : "Lithuania", "val": "Belorussian"},
 {"country" : "Lithuania", "val": "Lithuanian"},
 {"country" : "Lithuania", "val": "Polish"},
 {"country" : "Lithuania", "val": "Russian"},
 {"country" : "Lithuania", "val": "Ukrainian"},
 {"country" : "Luxembourg", "val": "French"},
 {"country" : "Luxembourg", "val": "German"},
 {"country" : "Luxembourg", "val": "Italian"},
 {"country" : "Luxembourg", "val": "Luxembourgish"},
 {"country" : "Luxembourg", "val": "Portuguese"},
 {"country" : "Latvia", "val": "Belorussian"},
 {"country" : "Latvia", "val": "Latvian"},
 {"country" : "Latvia", "val": "Lithuanian"},
 {"country" : "Latvia", "val": "Polish"},
 {"country" : "Latvia", "val": "Russian"},
 {"country" : "Latvia", "val": "Ukrainian"},
 {"country" : "Macao", "val": "Canton Chinese"},
 {"country" : "Macao", "val": "English"},
 {"country" : "Macao", "val": "Mandarin Chinese"},
 {"country" : "Macao", "val": "Portuguese"},
 {"country" : "Morocco", "val": "Arabic"},
 {"country" : "Morocco", "val": "Berberi"},
 {"country" : "Monaco", "val": "English"},
 {"country" : "Monaco", "val": "French"},
 {"country" : "Monaco", "val": "Italian"},
 {"country" : "Monaco", "val": "Monegasque"},
 {"country" : "Moldova", "val": "Bulgariana"},
 {"country" : "Moldova", "val": "Gagauzi"},
 {"country" : "Moldova", "val": "Romanian"},
 {"country" : "Moldova", "val": "Russian"},
 {"country" : "Moldova", "val": "Ukrainian"},
 {"country" : "Madagascar", "val": "French"},
 {"country" : "Madagascar", "val": "Malagasy"},
 {"country" : "Maldives", "val": "Dhivehi"},
 {"country" : "Maldives", "val": "English"},
 {"country" : "Mexico", "val": "Mixtec"},
 {"country" : "Mexico", "val": "Náhuatl"},
 {"country" : "Mexico", "val": "Otomí"},
 {"country" : "Mexico", "val": "Spanish"},
 {"country" : "Mexico", "val": "Yucatec"},
 {"country" : "Mexico", "val": "Zapotec"},
 {"country" : "Marshall Islands", "val": "English"},
 {"country" : "Marshall Islands", "val": "Marshallese"},
 {"country" : "Macedonia", "val": "Albaniana"},
 {"country" : "Macedonia", "val": "Macedonian"},
 {"country" : "Macedonia", "val": "Romani"},
 {"country" : "Macedonia", "val": "Serbo-Croatian"},
 {"country" : "Macedonia", "val": "Turkish"},
 {"country" : "Mali", "val": "Bambara"},
 {"country" : "Mali", "val": "Ful"},
 {"country" : "Mali", "val": "Senufo and Minianka"},
 {"country" : "Mali", "val": "Songhai"},
 {"country" : "Mali", "val": "Soninke"},
 {"country" : "Mali", "val": "Tamashek"},
 {"country" : "Malta", "val": "English"},
 {"country" : "Malta", "val": "Maltese"},
 {"country" : "Myanmar", "val": "Burmese"},
 {"country" : "Myanmar", "val": "Chin"},
 {"country" : "Myanmar", "val": "Kachin"},
 {"country" : "Myanmar", "val": "Karen"},
 {"country" : "Myanmar", "val": "Kayah"},
 {"country" : "Myanmar", "val": "Mon"},
 {"country" : "Myanmar", "val": "Rakhine"},
 {"country" : "Myanmar", "val": "Shan"},
 {"country" : "Mongolia", "val": "Bajad"},
 {"country" : "Mongolia", "val": "Buryat"},
 {"country" : "Mongolia", "val": "Dariganga"},
 {"country" : "Mongolia", "val": "Dorbet"},
 {"country" : "Mongolia", "val": "Kazakh"},
 {"country" : "Mongolia", "val": "Mongolian"},
 {"country" : "Northern Mariana Islands", "val": "Carolinian"},
 {"country" : "Northern Mariana Islands", "val": "Chamorro"},
 {"country" : "Northern Mariana Islands", "val": "Chinese"},
 {"country" : "Northern Mariana Islands", "val": "English"},
 {"country" : "Northern Mariana Islands", "val": "Korean"},
 {"country" : "Northern Mariana Islands", "val": "Philippene Languages"},
 {"country" : "Mozambique", "val": "Chuabo"},
 {"country" : "Mozambique", "val": "Lomwe"},
 {"country" : "Mozambique", "val": "Makua"},
 {"country" : "Mozambique", "val": "Marendje"},
 {"country" : "Mozambique", "val": "Nyanja"},
 {"country" : "Mozambique", "val": "Ronga"},
 {"country" : "Mozambique", "val": "Sena"},
 {"country" : "Mozambique", "val": "Shona"},
 {"country" : "Mozambique", "val": "Tsonga"},
 {"country" : "Mozambique", "val": "Tswa"},
 {"country" : "Mauritania", "val": "Ful"},
 {"country" : "Mauritania", "val": "Hassaniya"},
 {"country" : "Mauritania", "val": "Soninke"},
 {"country" : "Mauritania", "val": "Tukulor"},
 {"country" : "Mauritania", "val": "Wolof"},
 {"country" : "Mauritania", "val": "Zenaga"},
 {"country" : "Montserrat", "val": "English"},
 {"country" : "Martinique", "val": "Creole French"},
 {"country" : "Martinique", "val": "French"},
 {"country" : "Mauritius", "val": "Bhojpuri"},
 {"country" : "Mauritius", "val": "Creole French"},
 {"country" : "Mauritius", "val": "French"},
 {"country" : "Mauritius", "val": "Hindi"},
 {"country" : "Mauritius", "val": "Marathi"},
 {"country" : "Mauritius", "val": "Tamil"},
 {"country" : "Malawi", "val": "Chichewa"},
 {"country" : "Malawi", "val": "Lomwe"},
 {"country" : "Malawi", "val": "Ngoni"},
 {"country" : "Malawi", "val": "Yao"},
 {"country" : "Malaysia", "val": "Chinese"},
 {"country" : "Malaysia", "val": "Dusun"},
 {"country" : "Malaysia", "val": "English"},
 {"country" : "Malaysia", "val": "Iban"},
 {"country" : "Malaysia", "val": "Malay"},
 {"country" : "Malaysia", "val": "Tamil"},
 {"country" : "Mayotte", "val": "French"},
 {"country" : "Mayotte", "val": "Mahoré"},
 {"country" : "Mayotte", "val": "Malagasy"},
 {"country" : "Namibia", "val": "Afrikaans"},
 {"country" : "Namibia", "val": "Caprivi"},
 {"country" : "Namibia", "val": "German"},
 {"country" : "Namibia", "val": "Herero"},
 {"country" : "Namibia", "val": "Kavango"},
 {"country" : "Namibia", "val": "Nama"},
 {"country" : "Namibia", "val": "Ovambo"},
 {"country" : "Namibia", "val": "San"},
 {"country" : "New Caledonia", "val": "French"},
 {"country" : "New Caledonia", "val": "Malenasian Languages"},
 {"country" : "New Caledonia", "val": "Polynesian Languages"},
 {"country" : "Niger", "val": "Ful"},
 {"country" : "Niger", "val": "Hausa"},
 {"country" : "Niger", "val": "Kanuri"},
 {"country" : "Niger", "val": "Songhai-zerma"},
 {"country" : "Niger", "val": "Tamashek"},
 {"country" : "Norfolk Island", "val": "English"},
 {"country" : "Nigeria", "val": "Bura"},
 {"country" : "Nigeria", "val": "Edo"},
 {"country" : "Nigeria", "val": "Ful"},
 {"country" : "Nigeria", "val": "Hausa"},
 {"country" : "Nigeria", "val": "Ibibio"},
 {"country" : "Nigeria", "val": "Ibo"},
 {"country" : "Nigeria", "val": "Ijo"},
 {"country" : "Nigeria", "val": "Joruba"},
 {"country" : "Nigeria", "val": "Kanuri"},
 {"country" : "Nigeria", "val": "Tiv"},
 {"country" : "Nicaragua", "val": "Creole English"},
 {"country" : "Nicaragua", "val": "Miskito"},
 {"country" : "Nicaragua", "val": "Spanish"},
 {"country" : "Nicaragua", "val": "Sumo"},
 {"country" : "Niue", "val": "English"},
 {"country" : "Niue", "val": "Niue"},
 {"country" : "Netherlands", "val": "Arabic"},
 {"country" : "Netherlands", "val": "Dutch"},
 {"country" : "Netherlands", "val": "Fries"},
 {"country" : "Netherlands", "val": "Turkish"},
 {"country" : "Norway", "val": "Danish"},
 {"country" : "Norway", "val": "English"},
 {"country" : "Norway", "val": "Norwegian"},
 {"country" : "Norway", "val": "Saame"},
 {"country" : "Norway", "val": "Swedish"},
 {"country" : "Nepal", "val": "Bhojpuri"},
 {"country" : "Nepal", "val": "Hindi"},
 {"country" : "Nepal", "val": "Maithili"},
 {"country" : "Nepal", "val": "Nepali"},
 {"country" : "Nepal", "val": "Newari"},
 {"country" : "Nepal", "val": "Tamang"},
 {"country" : "Nepal", "val": "Tharu"},
 {"country" : "Nauru", "val": "Chinese"},
 {"country" : "Nauru", "val": "English"},
 {"country" : "Nauru", "val": "Kiribati"},
 {"country" : "Nauru", "val": "Nauru"},
 {"country" : "Nauru", "val": "Tuvalu"},
 {"country" : "New Zealand", "val": "English"},
 {"country" : "New Zealand", "val": "Maori"},
 {"country" : "Oman", "val": "Arabic"},
 {"country" : "Oman", "val": "Balochi"},
 {"country" : "Pakistan", "val": "Balochi"},
 {"country" : "Pakistan", "val": "Brahui"},
 {"country" : "Pakistan", "val": "Hindko"},
 {"country" : "Pakistan", "val": "Pashto"},
 {"country" : "Pakistan", "val": "Punjabi"},
 {"country" : "Pakistan", "val": "Saraiki"},
 {"country" : "Pakistan", "val": "Sindhi"},
 {"country" : "Pakistan", "val": "Urdu"},
 {"country" : "Panama", "val": "Arabic"},
 {"country" : "Panama", "val": "Creole English"},
 {"country" : "Panama", "val": "Cuna"},
 {"country" : "Panama", "val": "Embera"},
 {"country" : "Panama", "val": "Guaymí"},
 {"country" : "Panama", "val": "Spanish"},
 {"country" : "Pitcairn", "val": "Pitcairnese"},
 {"country" : "Peru", "val": "Aimará"},
 {"country" : "Peru", "val": "Ketua"},
 {"country" : "Peru", "val": "Spanish"},
 {"country" : "Philippines", "val": "Bicol"},
 {"country" : "Philippines", "val": "Cebuano"},
 {"country" : "Philippines", "val": "Hiligaynon"},
 {"country" : "Philippines", "val": "Ilocano"},
 {"country" : "Philippines", "val": "Maguindanao"},
 {"country" : "Philippines", "val": "Maranao"},
 {"country" : "Philippines", "val": "Pampango"},
 {"country" : "Philippines", "val": "Pangasinan"},
 {"country" : "Philippines", "val": "Pilipino"},
 {"country" : "Philippines", "val": "Waray-waray"},
 {"country" : "Palau", "val": "Chinese"},
 {"country" : "Palau", "val": "English"},
 {"country" : "Palau", "val": "Palau"},
 {"country" : "Palau", "val": "Philippene Languages"},
 {"country" : "Papua New Guinea", "val": "Malenasian Languages"},
 {"country" : "Papua New Guinea", "val": "Papuan Languages"},
 {"country" : "Poland", "val": "Belorussian"},
 {"country" : "Poland", "val": "German"},
 {"country" : "Poland", "val": "Polish"},
 {"country" : "Poland", "val": "Ukrainian"},
 {"country" : "Puerto Rico", "val": "English"},
 {"country" : "Puerto Rico", "val": "Spanish"},
 {"country" : "North Korea", "val": "Chinese"},
 {"country" : "North Korea", "val": "Korean"},
 {"country" : "Portugal", "val": "Portuguese"},
 {"country" : "Paraguay", "val": "German"},
 {"country" : "Paraguay", "val": "Guaraní"},
 {"country" : "Paraguay", "val": "Portuguese"},
 {"country" : "Paraguay", "val": "Spanish"},
 {"country" : "Palestine", "val": "Arabic"},
 {"country" : "Palestine", "val": "Hebrew"},
 {"country" : "French Polynesia", "val": "Chinese"},
 {"country" : "French Polynesia", "val": "French"},
 {"country" : "French Polynesia", "val": "Tahitian"},
 {"country" : "Qatar", "val": "Arabic"},
 {"country" : "Qatar", "val": "Urdu"},
 {"country" : "Reunion", "val": "Chinese"},
 {"country" : "Reunion", "val": "Comorian"},
 {"country" : "Reunion", "val": "Creole French"},
 {"country" : "Reunion", "val": "Malagasy"},
 {"country" : "Reunion", "val": "Tamil"},
 {"country" : "Romania", "val": "German"},
 {"country" : "Romania", "val": "Hungarian"},
 {"country" : "Romania", "val": "Romani"},
 {"country" : "Romania", "val": "Romanian"},
 {"country" : "Romania", "val": "Serbo-Croatian"},
 {"country" : "Romania", "val": "Ukrainian"},
 {"country" : "Russian Federation", "val": "Avarian"},
 {"country" : "Russian Federation", "val": "Bashkir"},
 {"country" : "Russian Federation", "val": "Belorussian"},
 {"country" : "Russian Federation", "val": "Chechen"},
 {"country" : "Russian Federation", "val": "Chuvash"},
 {"country" : "Russian Federation", "val": "Kazakh"},
 {"country" : "Russian Federation", "val": "Mari"},
 {"country" : "Russian Federation", "val": "Mordva"},
 {"country" : "Russian Federation", "val": "Russian"},
 {"country" : "Russian Federation", "val": "Tatar"},
 {"country" : "Russian Federation", "val": "Udmur"},
 {"country" : "Russian Federation", "val": "Ukrainian"},
 {"country" : "Rwanda", "val": "French"},
 {"country" : "Rwanda", "val": "Rwanda"},
 {"country" : "Saudi Arabia", "val": "Arabic"},
 {"country" : "Sudan", "val": "Arabic"},
 {"country" : "Sudan", "val": "Bari"},
 {"country" : "Sudan", "val": "Beja"},
 {"country" : "Sudan", "val": "Chilluk"},
 {"country" : "Sudan", "val": "Dinka"},
 {"country" : "Sudan", "val": "Fur"},
 {"country" : "Sudan", "val": "Lotuko"},
 {"country" : "Sudan", "val": "Nubian Languages"},
 {"country" : "Sudan", "val": "Nuer"},
 {"country" : "Sudan", "val": "Zande"},
 {"country" : "Senegal", "val": "Diola"},
 {"country" : "Senegal", "val": "Ful"},
 {"country" : "Senegal", "val": "Malinke"},
 {"country" : "Senegal", "val": "Serer"},
 {"country" : "Senegal", "val": "Soninke"},
 {"country" : "Senegal", "val": "Wolof"},
 {"country" : "Singapore", "val": "Chinese"},
 {"country" : "Singapore", "val": "Malay"},
 {"country" : "Singapore", "val": "Tamil"},
 {"country" : "Saint Helena", "val": "English"},
 {"country" : "Svalbard and Jan Mayen", "val": "Norwegian"},
 {"country" : "Svalbard and Jan Mayen", "val": "Russian"},
 {"country" : "Solomon Islands", "val": "Malenasian Languages"},
 {"country" : "Solomon Islands", "val": "Papuan Languages"},
 {"country" : "Solomon Islands", "val": "Polynesian Languages"},
 {"country" : "Sierra Leone", "val": "Bullom-sherbro"},
 {"country" : "Sierra Leone", "val": "Ful"},
 {"country" : "Sierra Leone", "val": "Kono-vai"},
 {"country" : "Sierra Leone", "val": "Kuranko"},
 {"country" : "Sierra Leone", "val": "Limba"},
 {"country" : "Sierra Leone", "val": "Mende"},
 {"country" : "Sierra Leone", "val": "Temne"},
 {"country" : "Sierra Leone", "val": "Yalunka"},
 {"country" : "El Salvador", "val": "Nahua"},
 {"country" : "El Salvador", "val": "Spanish"},
 {"country" : "San Marino", "val": "Italian"},
 {"country" : "Somalia", "val": "Arabic"},
 {"country" : "Somalia", "val": "Somali"},
 {"country" : "Saint Pierre and Miquelon", "val": "French"},
 {"country" : "Sao Tome and Principe", "val": "Crioulo"},
 {"country" : "Sao Tome and Principe", "val": "French"},
 {"country" : "Suriname", "val": "Hindi"},
 {"country" : "Suriname", "val": "Sranantonga"},
 {"country" : "Slovakia", "val": "Czech and Moravian"},
 {"country" : "Slovakia", "val": "Hungarian"},
 {"country" : "Slovakia", "val": "Romani"},
 {"country" : "Slovakia", "val": "Slovak"},
 {"country" : "Slovakia", "val": "Ukrainian and Russian"},
 {"country" : "Slovenia", "val": "Hungarian"},
 {"country" : "Slovenia", "val": "Serbo-Croatian"},
 {"country" : "Slovenia", "val": "Slovene"},
 {"country" : "Sweden", "val": "Arabic"},
 {"country" : "Sweden", "val": "Finnish"},
 {"country" : "Sweden", "val": "Norwegian"},
 {"country" : "Sweden", "val": "Southern Slavic Languages"},
 {"country" : "Sweden", "val": "Spanish"},
 {"country" : "Sweden", "val": "Swedish"},
 {"country" : "Swaziland", "val": "Swazi"},
 {"country" : "Swaziland", "val": "Zulu"},
 {"country" : "Seychelles", "val": "English"},
 {"country" : "Seychelles", "val": "French"},
 {"country" : "Seychelles", "val": "Seselwa"},
 {"country" : "Syria", "val": "Arabic"},
 {"country" : "Syria", "val": "Kurdish"},
 {"country" : "Turks and Caicos Islands", "val": "English"},
 {"country" : "Chad", "val": "Arabic"},
 {"country" : "Chad", "val": "Gorane"},
 {"country" : "Chad", "val": "Hadjarai"},
 {"country" : "Chad", "val": "Kanem-bornu"},
 {"country" : "Chad", "val": "Mayo-kebbi"},
 {"country" : "Chad", "val": "Ouaddai"},
 {"country" : "Chad", "val": "Sara"},
 {"country" : "Chad", "val": "Tandjile"},
 {"country" : "Togo", "val": "Ane"},
 {"country" : "Togo", "val": "Ewe"},
 {"country" : "Togo", "val": "Gurma"},
 {"country" : "Togo", "val": "Kabyé"},
 {"country" : "Togo", "val": "Kotokoli"},
 {"country" : "Togo", "val": "Moba"},
 {"country" : "Togo", "val": "Naudemba"},
 {"country" : "Togo", "val": "Watyi"},
 {"country" : "Thailand", "val": "Chinese"},
 {"country" : "Thailand", "val": "Khmer"},
 {"country" : "Thailand", "val": "Kuy"},
 {"country" : "Thailand", "val": "Lao"},
 {"country" : "Thailand", "val": "Malay"},
 {"country" : "Thailand", "val": "Thai"},
 {"country" : "Tajikistan", "val": "Russian"},
 {"country" : "Tajikistan", "val": "Tadzhik"},
 {"country" : "Tajikistan", "val": "Uzbek"},
 {"country" : "Tokelau", "val": "English"},
 {"country" : "Tokelau", "val": "Tokelau"},
 {"country" : "Turkmenistan", "val": "Kazakh"},
 {"country" : "Turkmenistan", "val": "Russian"},
 {"country" : "Turkmenistan", "val": "Turkmenian"},
 {"country" : "Turkmenistan", "val": "Uzbek"},
 {"country" : "East Timor", "val": "Portuguese"},
 {"country" : "East Timor", "val": "Sunda"},
 {"country" : "Tonga", "val": "English"},
 {"country" : "Tonga", "val": "Tongan"},
 {"country" : "Trinidad and Tobago", "val": "Creole English"},
 {"country" : "Trinidad and Tobago", "val": "English"},
 {"country" : "Trinidad and Tobago", "val": "Hindi"},
 {"country" : "Tunisia", "val": "Arabic"},
 {"country" : "Tunisia", "val": "Arabic-French"},
 {"country" : "Tunisia", "val": "Arabic-French-English"},
 {"country" : "Turkey", "val": "Arabic"},
 {"country" : "Turkey", "val": "Kurdish"},
 {"country" : "Turkey", "val": "Turkish"},
 {"country" : "Tuvalu", "val": "English"},
 {"country" : "Tuvalu", "val": "Kiribati"},
 {"country" : "Tuvalu", "val": "Tuvalu"},
 {"country" : "Taiwan", "val": "Ami"},
 {"country" : "Taiwan", "val": "Atayal"},
 {"country" : "Taiwan", "val": "Hakka"},
 {"country" : "Taiwan", "val": "Mandarin Chinese"},
 {"country" : "Taiwan", "val": "Min"},
 {"country" : "Taiwan", "val": "Paiwan"},
 {"country" : "Tanzania", "val": "Chaga and Pare"},
 {"country" : "Tanzania", "val": "Gogo"},
 {"country" : "Tanzania", "val": "Ha"},
 {"country" : "Tanzania", "val": "Haya"},
 {"country" : "Tanzania", "val": "Hehet"},
 {"country" : "Tanzania", "val": "Luguru"},
 {"country" : "Tanzania", "val": "Makonde"},
 {"country" : "Tanzania", "val": "Nyakusa"},
 {"country" : "Tanzania", "val": "Nyamwesi"},
 {"country" : "Tanzania", "val": "Shambala"},
 {"country" : "Tanzania", "val": "Swahili"},
 {"country" : "Uganda", "val": "Acholi"},
 {"country" : "Uganda", "val": "Ganda"},
 {"country" : "Uganda", "val": "Gisu"},
 {"country" : "Uganda", "val": "Kiga"},
 {"country" : "Uganda", "val": "Lango"},
 {"country" : "Uganda", "val": "Lugbara"},
 {"country" : "Uganda", "val": "Nkole"},
 {"country" : "Uganda", "val": "Rwanda"},
 {"country" : "Uganda", "val": "Soga"},
 {"country" : "Uganda", "val": "Teso"},
 {"country" : "Ukraine", "val": "Belorussian"},
 {"country" : "Ukraine", "val": "Bulgariana"},
 {"country" : "Ukraine", "val": "Hungarian"},
 {"country" : "Ukraine", "val": "Polish"},
 {"country" : "Ukraine", "val": "Romanian"},
 {"country" : "Ukraine", "val": "Russian"},
 {"country" : "Ukraine", "val": "Ukrainian"},
 {"country" : "United States Minor Outlying Islands", "val": "English"},
 {"country" : "Uruguay", "val": "Spanish"},
 {"country" : "United States", "val": "Chinese"},
 {"country" : "United States", "val": "English"},
 {"country" : "United States", "val": "French"},
 {"country" : "United States", "val": "German"},
 {"country" : "United States", "val": "Italian"},
 {"country" : "United States", "val": "Japanese"},
 {"country" : "United States", "val": "Korean"},
 {"country" : "United States", "val": "Polish"},
 {"country" : "United States", "val": "Portuguese"},
 {"country" : "United States", "val": "Spanish"},
 {"country" : "United States", "val": "Tagalog"},
 {"country" : "United States", "val": "Vietnamese"},
 {"country" : "Uzbekistan", "val": "Karakalpak"},
 {"country" : "Uzbekistan", "val": "Kazakh"},
 {"country" : "Uzbekistan", "val": "Russian"},
 {"country" : "Uzbekistan", "val": "Tadzhik"},
 {"country" : "Uzbekistan", "val": "Tatar"},
 {"country" : "Uzbekistan", "val": "Uzbek"},
 {"country" : "Holy See (Vatican City State)", "val": "Italian"},
 {"country" : "Saint Vincent and the Grenadines", "val": "Creole English"},
 {"country" : "Saint Vincent and the Grenadines", "val": "English"},
 {"country" : "Venezuela", "val": "Goajiro"},
 {"country" : "Venezuela", "val": "Spanish"},
 {"country" : "Venezuela", "val": "Warrau"},
 {"country" : "Virgin Islands, British", "val": "English"},
 {"country" : "Virgin Islands, U.S.", "val": "English"},
 {"country" : "Virgin Islands, U.S.", "val": "French"},
 {"country" : "Virgin Islands, U.S.", "val": "Spanish"},
 {"country" : "Vietnam", "val": "Chinese"},
 {"country" : "Vietnam", "val": "Khmer"},
 {"country" : "Vietnam", "val": "Man"},
 {"country" : "Vietnam", "val": "Miao"},
 {"country" : "Vietnam", "val": "Muong"},
 {"country" : "Vietnam", "val": "Nung"},
 {"country" : "Vietnam", "val": "Thai"},
 {"country" : "Vietnam", "val": "Tho"},
 {"country" : "Vietnam", "val": "Vietnamese"},
 {"country" : "Vanuatu", "val": "Bislama"},
 {"country" : "Vanuatu", "val": "English"},
 {"country" : "Vanuatu", "val": "French"},
 {"country" : "Wallis and Futuna", "val": "Futuna"},
 {"country" : "Wallis and Futuna", "val": "Wallis"},
 {"country" : "Samoa", "val": "English"},
 {"country" : "Samoa", "val": "Samoan"},
 {"country" : "Samoa", "val": "Samoan-English"},
 {"country" : "Yemen", "val": "Arabic"},
 {"country" : "Yemen", "val": "Soqutri"},
 {"country" : "Yugoslavia", "val": "Albaniana"},
 {"country" : "Yugoslavia", "val": "Hungarian"},
 {"country" : "Yugoslavia", "val": "Macedonian"},
 {"country" : "Yugoslavia", "val": "Romani"},
 {"country" : "Yugoslavia", "val": "Serbo-Croatian"},
 {"country" : "Yugoslavia", "val": "Slovak"},
 {"country" : "South Africa", "val": "Afrikaans"},
 {"country" : "South Africa", "val": "English"},
 {"country" : "South Africa", "val": "Ndebele"},
 {"country" : "South Africa", "val": "Northsotho"},
 {"country" : "South Africa", "val": "Southsotho"},
 {"country" : "South Africa", "val": "Swazi"},
 {"country" : "South Africa", "val": "Tsonga"},
 {"country" : "South Africa", "val": "Tswana"},
 {"country" : "South Africa", "val": "Venda"},
 {"country" : "South Africa", "val": "Xhosa"},
 {"country" : "South Africa", "val": "Zulu"},
 {"country" : "Zambia", "val": "Bemba"},
 {"country" : "Zambia", "val": "Chewa"},
 {"country" : "Zambia", "val": "Lozi"},
 {"country" : "Zambia", "val": "Nsenga"},
 {"country" : "Zambia", "val": "Nyanja"},
 {"country" : "Zambia", "val": "Tongan"},
 {"country" : "Zimbabwe", "val": "English"},
 {"country" : "Zimbabwe", "val": "Ndebele"},
 {"country" : "Zimbabwe", "val": "Nyanja"},
 {"country" : "Zimbabwe", "val": "Shona"}
 ]
